structest/__init__.py
structest/structest.py
structest-0.0.1.dist-info/METADATA
structest-0.0.1.dist-info/WHEEL
structest-0.0.1.dist-info/entry_points.txt
structest-0.0.1.dist-info/licenses/LICENSE
structest-0.0.1.dist-info/RECORD
