Metadata-Version: 2.4
Name: structest
Version: 0.0.1
License-File: LICENSE
